dmf_device_ui/__init__.py
dmf_device_ui/canvas.py
dmf_device_ui/client.py
dmf_device_ui/notifier.py
dmf_device_ui/options.py
dmf_device_ui/plugin.py
dmf_device_ui/view.py
dmf_device_ui/.ipynb_checkpoints/Example - tesselate DMF device electrodes-checkpoint.ipynb
dmf_device_ui/bin/__init__.py
dmf_device_ui/bin/device_view.py
dmf_device_ui/bin/test.py
dmf_device_ui/examples/Example - scale and center drawing-Copy1.ipynb
dmf_device_ui/examples/Example - scale and center drawing.ipynb
dmf_device_ui/examples/Example - tesselate DMF device electrodes.ipynb
dmf_device_ui/examples/.ipynb_checkpoints/Example - scale and center drawing-Copy1-checkpoint.ipynb
dmf_device_ui/examples/.ipynb_checkpoints/Example - scale and center drawing-checkpoint.ipynb
dmf_device_ui/examples/.ipynb_checkpoints/Example - tesselate DMF device electrodes-checkpoint.ipynb
dmf_device_ui/examples/static/device.svg
dmf_device_ui/examples/static/device.wconnections.svg
dmf_device_ui-0.2.post104.dist-info/DESCRIPTION.rst
dmf_device_ui-0.2.post104.dist-info/METADATA
dmf_device_ui-0.2.post104.dist-info/RECORD
dmf_device_ui-0.2.post104.dist-info/WHEEL
dmf_device_ui-0.2.post104.dist-info/metadata.json
dmf_device_ui-0.2.post104.dist-info/pbr.json
dmf_device_ui-0.2.post104.dist-info/top_level.txt
